stackzilla/provider/aws/ec2/__init__.py
stackzilla/provider/aws/ec2/instance.py
stackzilla/provider/aws/ec2/key_pair.py
stackzilla/provider/aws/ec2/security_group.py
stackzilla/provider/aws/eks/__init__.py
stackzilla/provider/aws/eks/cluster.py
stackzilla/provider/aws/eks/node_group.py
stackzilla/provider/aws/utils/__init__.py
stackzilla/provider/aws/utils/arn.py
stackzilla/provider/aws/utils/instances.py
stackzilla/provider/aws/utils/regions.py
stackzilla/provider/aws/utils/tags.py
stackzilla_provider_aws-0.2.1.dist-info/LICENSE
stackzilla_provider_aws-0.2.1.dist-info/METADATA
stackzilla_provider_aws-0.2.1.dist-info/WHEEL
stackzilla_provider_aws-0.2.1.dist-info/top_level.txt
stackzilla_provider_aws-0.2.1.dist-info/RECORD
