Metadata-Version: 2.1
Name: stackzilla-provider-aws
Version: 0.2.1
Summary: An ORM for your application stack.
Home-page: https://github.com/Stackzilla/stackzilla-provider-aws
Author: Zimventures, LLC
Author-email: yourname@yourdomain.com
License: GNU Affero General Public License v3
Platform: any
Classifier: Development Status :: 3 - Alpha
Classifier: Environment :: Console
Classifier: Intended Audience :: Developers
Classifier: License :: OSI Approved :: GNU Affero General Public License v3
Classifier: Operating System :: POSIX
Classifier: Programming Language :: Python :: 3
Classifier: Programming Language :: Python :: 3.8
Classifier: Programming Language :: Python :: 3.9
Classifier: Programming Language :: Python :: 3.10
Classifier: Topic :: Software Development :: Libraries
Requires-Python: >3.7
License-File: LICENSE
Requires-Dist: boto3
Requires-Dist: stackzilla
Provides-Extra: dev
Requires-Dist: invoke (==1.7.1) ; extra == 'dev'
Requires-Dist: wheel ; extra == 'dev'
Provides-Extra: test
Requires-Dist: coverage (==6.5.0) ; extra == 'test'
Requires-Dist: invoke (==1.7.1) ; extra == 'test'
Requires-Dist: isort (==5.10.1) ; extra == 'test'
Requires-Dist: mypy (==0.971) ; extra == 'test'
Requires-Dist: mypy-extensions (==0.4.3) ; extra == 'test'
Requires-Dist: pydocstyle (==6.1.1) ; extra == 'test'
Requires-Dist: pyflakes (==2.5.0) ; extra == 'test'
Requires-Dist: pylint ; extra == 'test'
Requires-Dist: pytest ; extra == 'test'
Requires-Dist: pytest-cov ; extra == 'test'
